LICENSE
MANIFEST.in
README.rst
ml_post.py
ml_post_ui.py
ml_update_guidata.py
mui.py
pyproject.toml
setup.py
marlowe_ui/__init__.py
marlowe_ui/axis.py
marlowe_ui/balloonhelp.py
marlowe_ui/data.py
marlowe_ui/format_fort.py
marlowe_ui/gui_atom.py
marlowe_ui/gui_atomtbl.py
marlowe_ui/gui_filepath.py
marlowe_ui/gui_layer_surf.py
marlowe_ui/gui_modl.py
marlowe_ui/gui_outp.py
marlowe_ui/gui_proj.py
marlowe_ui/gui_proj_elem.py
marlowe_ui/gui_root.py
marlowe_ui/gui_selectelem.py
marlowe_ui/gui_site_elem.py
marlowe_ui/gui_size.py
marlowe_ui/gui_size_body.py
marlowe_ui/gui_surf.py
marlowe_ui/gui_xtal.py
marlowe_ui/gui_xtal_layer.py
marlowe_ui/gui_xtal_layer_elem.py
marlowe_ui/json_conv.py
marlowe_ui/layoutmode.py
marlowe_ui/logconsole.py
marlowe_ui/profile.py
marlowe_ui/run.py
marlowe_ui/scon.py
marlowe_ui/smart_argparse.py
marlowe_ui/spawn_diag.py
marlowe_ui/to_marlowe.py
marlowe_ui/version.py
marlowe_ui/vpar.py
marlowe_ui/vpar_moliere.py
marlowe_ui.egg-info/PKG-INFO
marlowe_ui.egg-info/SOURCES.txt
marlowe_ui.egg-info/dependency_links.txt
marlowe_ui.egg-info/not-zip-safe
marlowe_ui.egg-info/requires.txt
marlowe_ui.egg-info/top_level.txt
marlowe_ui/contrib/__init__.py
marlowe_ui/contrib/bundlepmw/Pmw.py
marlowe_ui/contrib/bundlepmw/PmwBlt.py
marlowe_ui/contrib/bundlepmw/PmwColor.py
marlowe_ui/contrib/bundlepmw/__init__.py
marlowe_ui/contrib/bundlepmw/bundlepmw.py
marlowe_ui/doc/development_QA.html
marlowe_ui/doc/development_QA.rst
marlowe_ui/doc/packaging.html
marlowe_ui/doc/packaging.rst
marlowe_ui/doc/virtualenv_win.html
marlowe_ui/doc/virtualenv_win.rst
marlowe_ui/examples/SRIM_compatible/Si400keV-Si100-1000trials-look4.dat
marlowe_ui/examples/SRIM_compatible/Si400keV-Si100-1000trials-look4.json
marlowe_ui/examples/SRIM_compatible/Si400keV-Siamo-1000trials-look4.dat
marlowe_ui/examples/SRIM_compatible/Si400keV-Siamo-1000trials-look4.json
marlowe_ui/examples/mui_compat/README.html
marlowe_ui/examples/mui_compat/README.rst
marlowe_ui/examples/mui_compat/orig/test_2td1.dat
marlowe_ui/examples/mui_compat/orig/test_3td1.dat
marlowe_ui/examples/mui_compat/orig/test_a1.dat
marlowe_ui/examples/mui_compat/orig/test_a2.dat
marlowe_ui/examples/mui_compat/orig/test_b1.dat
