Metadata-Version: 1.1
Name: marlowe-ui
Version: 0.5.19
Summary: UI program for Marlowe input data file
Home-page: https://bitbucket.org/marlowe_ui/
Author: Takaaki AOKI
Author-email: aoki.takaaki@nagoya-u.jp
License: UNKNOWN
Platform: UNKNOWN
Classifier: Programming Language :: Python
Classifier: Programming Language :: Python :: 3.8
Classifier: License :: OSI Approved :: MIT License
Classifier: Development Status :: 4 - Beta
Classifier: Environment :: Other Environment
Classifier: Intended Audience :: Science/Research
Classifier: Operating System :: OS Independent
Classifier: Topic :: Scientific/Engineering :: Physics
